edc_subject_dashboard/__init__.py
edc_subject_dashboard/apps.py
edc_subject_dashboard/auths.py
edc_subject_dashboard/dashboard_templates.py
edc_subject_dashboard/middleware.py
edc_subject_dashboard/models.py
edc_subject_dashboard/requisition_labels.py
edc_subject_dashboard/requisition_report.py
edc_subject_dashboard/requisition_verifier.py
edc_subject_dashboard/system_checks.py
edc_subject_dashboard/urls.py
edc_subject_dashboard/wsgi.py
edc_subject_dashboard/locale/sw/LC_MESSAGES/django.mo
edc_subject_dashboard/locale/sw/LC_MESSAGES/django.po
edc_subject_dashboard/migrations/0001_initial.py
edc_subject_dashboard/migrations/0002_alter_edcpermissions_device_created_and_more.py
edc_subject_dashboard/migrations/0003_edcpermissions_locale_created_and_more.py
edc_subject_dashboard/migrations/__init__.py
edc_subject_dashboard/templates/edc_subject_dashboard/appointment_in_progress.html
edc_subject_dashboard/templates/edc_subject_dashboard/appointment_status.html
edc_subject_dashboard/templates/edc_subject_dashboard/dashboard.html
edc_subject_dashboard/templates/edc_subject_dashboard/dashboard_button.html
edc_subject_dashboard/templates/edc_subject_dashboard/print_requisition_popover.html
edc_subject_dashboard/templates/edc_subject_dashboard/requisition_panel_actions.html
edc_subject_dashboard/templates/edc_subject_dashboard/buttons/appointment_button.html
edc_subject_dashboard/templates/edc_subject_dashboard/buttons/crf_button_group.html
edc_subject_dashboard/templates/edc_subject_dashboard/buttons/forms_button.html
edc_subject_dashboard/templates/edc_subject_dashboard/buttons/popover_list_item.html
edc_subject_dashboard/templates/edc_subject_dashboard/buttons/prn_button.html
edc_subject_dashboard/templates/edc_subject_dashboard/buttons/refresh_appointments_button.html
edc_subject_dashboard/templates/edc_subject_dashboard/buttons/refresh_data_collection_schedule_button.html
edc_subject_dashboard/templates/edc_subject_dashboard/buttons/requisition_button_group.html
edc_subject_dashboard-1.0.1.dist-info/licenses/AUTHORS.rst
edc_subject_dashboard-1.0.1.dist-info/licenses/LICENSE
edc_subject_dashboard-1.0.1.dist-info/METADATA
edc_subject_dashboard-1.0.1.dist-info/WHEEL
edc_subject_dashboard-1.0.1.dist-info/top_level.txt
edc_subject_dashboard-1.0.1.dist-info/RECORD
